setup.py
src/CustomeLibrary/Util.py
src/CustomeLibrary/__init__.py
src/CustomeLibrary.egg-info/PKG-INFO
src/CustomeLibrary.egg-info/SOURCES.txt
src/CustomeLibrary.egg-info/dependency_links.txt
src/CustomeLibrary.egg-info/top_level.txt