Metadata-Version: 1.2
Name: CustomeLibrary
Version: 0.0.3
Summary: CustomeLibrary for Robot Framework
Home-page: https://github.com/
Author: caiys
Author-email: caiys@asiainfo-net.com
License: MIT Licence
Keywords: CustomeLibrary for robotframework
Platform: any
Requires-Python: >=3.7
